LICENSE.md
README.md
setup.cfg
setup.py
src/CephQeSdk.egg-info/PKG-INFO
src/CephQeSdk.egg-info/SOURCES.txt
src/CephQeSdk.egg-info/dependency_links.txt
src/CephQeSdk.egg-info/requires.txt
src/CephQeSdk.egg-info/top_level.txt
src/CephQeSdk.egg-info/zip-safe
src/RhcsQeSdk/__init__.py
src/RhcsQeSdk/core/__init__.py
src/RhcsQeSdk/core/cli/__init__.py
src/RhcsQeSdk/core/cli/cli.py
src/RhcsQeSdk/core/cli/fabfile.py
src/RhcsQeSdk/core/cli/ceph/__init__.py
src/RhcsQeSdk/core/cli/ceph/application.py
src/RhcsQeSdk/core/cli/ceph/auth.py
src/RhcsQeSdk/core/cli/ceph/balancer.py
src/RhcsQeSdk/core/cli/ceph/blocklist.py
src/RhcsQeSdk/core/cli/ceph/ceph.py
src/RhcsQeSdk/core/cli/ceph/cephadm.py
src/RhcsQeSdk/core/cli/ceph/config.py
src/RhcsQeSdk/core/cli/ceph/config_key.py
src/RhcsQeSdk/core/cli/ceph/crush.py
src/RhcsQeSdk/core/cli/ceph/erasurecodeprofile.py
src/RhcsQeSdk/core/cli/ceph/health.py
src/RhcsQeSdk/core/cli/ceph/mds.py
src/RhcsQeSdk/core/cli/ceph/mgr.py
src/RhcsQeSdk/core/cli/ceph/module.py
src/RhcsQeSdk/core/cli/ceph/mon.py
src/RhcsQeSdk/core/cli/ceph/osd.py
src/RhcsQeSdk/core/cli/ceph/pg.py
src/RhcsQeSdk/core/cli/ceph/pool.py
src/RhcsQeSdk/core/cli/ceph/rule.py
src/RhcsQeSdk/core/cli/ceph/tier.py
src/RhcsQeSdk/core/cli/ceph/orch/__init__.py
src/RhcsQeSdk/core/cli/ceph/orch/daemon.py
src/RhcsQeSdk/core/cli/ceph/orch/host.py
src/RhcsQeSdk/core/cli/ceph/orch/label.py
src/RhcsQeSdk/core/cli/ceph/orch/maintanence.py
src/RhcsQeSdk/core/cli/ceph/orch/orch.py
src/RhcsQeSdk/core/cli/ceph/orch/osd.py
src/RhcsQeSdk/core/cli/ceph/orch/rm.py
src/RhcsQeSdk/core/cli/ceph/orch/upgrade.py
src/RhcsQeSdk/core/cli/rados/__init__.py
src/RhcsQeSdk/core/cli/rados/rados.py
src/RhcsQeSdk/core/cli/radosgw_admin/__init__.py
src/RhcsQeSdk/core/cli/radosgw_admin/bi.py
src/RhcsQeSdk/core/cli/radosgw_admin/bucket.py
src/RhcsQeSdk/core/cli/radosgw_admin/caps.py
src/RhcsQeSdk/core/cli/radosgw_admin/key.py
src/RhcsQeSdk/core/cli/radosgw_admin/log.py
src/RhcsQeSdk/core/cli/radosgw_admin/metadata.py
src/RhcsQeSdk/core/cli/radosgw_admin/object.py
src/RhcsQeSdk/core/cli/radosgw_admin/period.py
src/RhcsQeSdk/core/cli/radosgw_admin/pool.py
src/RhcsQeSdk/core/cli/radosgw_admin/quota.py
