Metadata-Version: 2.1
Name: CephQeSdk
Version: 1.0.0
Summary: RHCS QE SDK Library
Home-page: https://gitlab.cee.redhat.com/rhcs-qe/rhcs-qe-sdk
Author: Red Hat Inc.
Author-email: cephci@redhat.com
License: UNKNOWN
Platform: UNKNOWN
License-File: LICENSE.md
